test_package/__init__.py
test_package/core.py
darshika_test_package-0.0.3.dist-info/LICENSE
darshika_test_package-0.0.3.dist-info/METADATA
darshika_test_package-0.0.3.dist-info/WHEEL
darshika_test_package-0.0.3.dist-info/top_level.txt
darshika_test_package-0.0.3.dist-info/RECORD
